optischedule/__init__.py
optischedule-0.1.0a0.dist-info/WHEEL
optischedule-0.1.0a0.dist-info/METADATA
optischedule-0.1.0a0.dist-info/RECORD
