Metadata-Version: 2.3
Name: optischedule
Version: 0.1.0a0
Summary: Optimized scheduling.
Requires-Python: >=3.12
